.coveragerc
CHANGES.rst
CONTRIBUTORS.rst
MANIFEST.in
README.rst
bootstrap-buildout.py
bootstrap.py
buildout.cfg
setup.py
travis.cfg
docs/LICENSE.GPL
docs/LICENSE.rst
src/collective/__init__.py
src/collective.faceted.task.egg-info/PKG-INFO
src/collective.faceted.task.egg-info/SOURCES.txt
src/collective.faceted.task.egg-info/dependency_links.txt
src/collective.faceted.task.egg-info/entry_points.txt
src/collective.faceted.task.egg-info/namespace_packages.txt
src/collective.faceted.task.egg-info/not-zip-safe
src/collective.faceted.task.egg-info/requires.txt
src/collective.faceted.task.egg-info/top_level.txt
src/collective/faceted/__init__.py
src/collective/faceted/task/__init__.py
src/collective/faceted/task/adapters.py
src/collective/faceted/task/configure.zcml
src/collective/faceted/task/faceted_task_config.py
src/collective/faceted/task/faceted_task_config.xml
src/collective/faceted/task/interfaces.py
src/collective/faceted/task/overrides.zcml
src/collective/faceted/task/setuphandlers.py
src/collective/faceted/task/testing.py
src/collective/faceted/task/testing.zcml
src/collective/faceted/task/browser/__init__.py
src/collective/faceted/task/browser/config_view.py
src/collective/faceted/task/browser/configure.zcml
src/collective/faceted/task/browser/faceted_view.py
src/collective/faceted/task/browser/list_tasks.py
src/collective/faceted/task/browser/table.py
src/collective/faceted/task/browser/task_table_view.py
src/collective/faceted/task/browser/task_view.py
src/collective/faceted/task/browser/static/.gitkeep
src/collective/faceted/task/browser/static/faceted_task.css
src/collective/faceted/task/browser/templates/config_view.pt
src/collective/faceted/task/browser/templates/facetedtask_view.pt
src/collective/faceted/task/events/__init__.py
src/collective/faceted/task/events/configure.zcml
src/collective/faceted/task/events/task_events.py
src/collective/faceted/task/locales/collective.faceted.task.pot
src/collective/faceted/task/locales/eea.pot
src/collective/faceted/task/locales/update.sh
src/collective/faceted/task/locales/fr/LC_MESSAGES/collective.faceted.task.mo
src/collective/faceted/task/locales/fr/LC_MESSAGES/collective.faceted.task.po
src/collective/faceted/task/locales/fr/LC_MESSAGES/eea.mo
src/collective/faceted/task/locales/fr/LC_MESSAGES/eea.po
src/collective/faceted/task/profiles/base/componentregistry.xml
src/collective/faceted/task/profiles/base/metadata.xml
