Metadata-Version: 2.1
Name: collective.faceted.task
Version: 1.0.2
Summary: Faceted tools and view for tasks
Home-page: http://pypi.python.org/pypi/collective.faceted.task
Author: Franck NGAHA
Author-email: franck.o.ngaha@gmail.com
License: GPL V2
Keywords: Python Zope Plone
Classifier: Environment :: Web Environment
Classifier: Framework :: Plone
Classifier: Framework :: Plone :: 4.3
Classifier: Programming Language :: Python
Classifier: Programming Language :: Python :: 2.7
Classifier: Operating System :: OS Independent
Classifier: License :: OSI Approved :: GNU General Public License v2 (GPLv2)
Provides-Extra: test
